neorl/__init__.py
neorl/scripts.py
neorl/version.py
neorl/version.txt
neorl/benchmarks/__init__.py
neorl/benchmarks/cec08.py
neorl/benchmarks/cec17.py
neorl/benchmarks/classic.py
neorl/benchmarks/kp.py
neorl/benchmarks/qpower_model.py
neorl/benchmarks/reactivity_model.py
neorl/benchmarks/tsp.py
neorl/benchmarks/tools/__init__.py
neorl/benchmarks/tools/basic.py
neorl/benchmarks/tools/data.pkl
neorl/benchmarks/tools/data08.csv
neorl/benchmarks/tools/microreactor_alpha_wtd_gr.csv
neorl/benchmarks/tools/microreactor_configA_flux_wtd_b.csv
neorl/benchmarks/tools/microreactor_configB_flux_wtd_b.csv
neorl/benchmarks/tools/microreactor_power_model.h5
neorl/benchmarks/tools/transforms.py
neorl/evolu/__init__.py
neorl/evolu/aco.py
neorl/evolu/bat.py
neorl/evolu/crossover.py
neorl/evolu/cs.py
neorl/evolu/de.py
neorl/evolu/discrete.py
neorl/evolu/es.py
neorl/evolu/ga.py
neorl/evolu/gwo.py
neorl/evolu/hclpso.py
neorl/evolu/hho.py
neorl/evolu/jaya.py
neorl/evolu/mfo.py
neorl/evolu/mutation.py
neorl/evolu/pso.py
neorl/evolu/sa.py
neorl/evolu/ssa.py
neorl/evolu/ts.py
neorl/evolu/woa.py
neorl/evolu/xnes.py
neorl/evolu/runners/__init__.py
neorl/evolu/runners/ga.py
neorl/evolu/runners/sa.py
neorl/hybrid/__init__.py
neorl/hybrid/ackde.py
neorl/hybrid/aeo.py
neorl/hybrid/edev.py
neorl/hybrid/epso.py
neorl/hybrid/fneat.py
neorl/hybrid/nga.py
neorl/hybrid/nhho.py
neorl/hybrid/pesa.py
neorl/hybrid/pesa2.py
neorl/hybrid/pesax.py
neorl/hybrid/ppoes.py
neorl/hybrid/rneat.py
neorl/hybrid/edevcore/__init__.py
neorl/hybrid/edevcore/helpers.py
neorl/hybrid/ngacore/GA.py
neorl/hybrid/ngacore/Latin.py
neorl/hybrid/ngacore/RBFN.py
neorl/hybrid/ngacore/__init__.py
neorl/hybrid/nhhocore/Latin.py
neorl/hybrid/nhhocore/__init__.py
neorl/hybrid/nhhocore/hho.py
neorl/hybrid/nhhocore/nnmodel.py
neorl/hybrid/pesacore/__init__.py
neorl/hybrid/pesacore/de.py
neorl/hybrid/pesacore/er.py
neorl/hybrid/pesacore/es.py
neorl/hybrid/pesacore/gwo.py
neorl/hybrid/pesacore/pso.py
neorl/hybrid/pesacore/sa.py
neorl-1.8.dist-info/LICENSE
neorl-1.8.dist-info/METADATA
neorl-1.8.dist-info/WHEEL
neorl-1.8.dist-info/entry_points.txt
neorl-1.8.dist-info/top_level.txt
neorl-1.8.dist-info/RECORD
