Metadata-Version: 2.1
Name: neorl
Version: 1.8
Summary: NeuroEvolution Optimisation with Reinforcement Learning
Home-page: https://github.com/mradaideh/neorl
Author: Majdi I. Radaideh
Author-email: radaideh@mit.edu
License: MIT
Platform: UNKNOWN
Classifier: License :: OSI Approved :: MIT License
Classifier: Programming Language :: Python :: 3.5
Classifier: Programming Language :: Python :: 3.6
Classifier: Programming Language :: Python :: 3.7
Requires-Dist: tensorflow (==1.14.0)
Requires-Dist: numpy (==1.16.2)
Requires-Dist: gym (<0.17.0,>=0.15.4)
Requires-Dist: scikit-optimize (==0.8.1)
Requires-Dist: cloudpickle (>=1.2.2)
Requires-Dist: h5py (<2.10.0)
Requires-Dist: scikit-learn (<=0.24.2)
Requires-Dist: neat-python
Requires-Dist: xarray (==0.16)
Requires-Dist: protobuf (==3.20)
Requires-Dist: scipy
Requires-Dist: joblib
Requires-Dist: pandas
Requires-Dist: xlrd (==1.2.0)
Requires-Dist: matplotlib
Requires-Dist: pytest
Requires-Dist: pytest-cov
Requires-Dist: sphinx
Requires-Dist: sphinx-rtd-theme
Requires-Dist: sphinx-autobuild
Provides-Extra: docs
Requires-Dist: sphinx ; extra == 'docs'
Requires-Dist: sphinx-autobuild ; extra == 'docs'
Requires-Dist: sphinx-rtd-theme ; extra == 'docs'
Provides-Extra: tests
Requires-Dist: pytest ; extra == 'tests'
Requires-Dist: pytest-cov ; extra == 'tests'
Requires-Dist: pytest-env ; extra == 'tests'
Requires-Dist: pytest-xdist ; extra == 'tests'
Requires-Dist: pytype ; extra == 'tests'
